moltbook_cli/__init__.py
moltbook_cli/main.py
moltbook_cli-0.0.2.dist-info/METADATA
moltbook_cli-0.0.2.dist-info/WHEEL
moltbook_cli-0.0.2.dist-info/entry_points.txt
moltbook_cli-0.0.2.dist-info/licenses/LICENSE
moltbook_cli-0.0.2.dist-info/RECORD
