Metadata-Version: 2.4
Name: moltbook-cli
Version: 0.0.2
Summary: Use CLI to interact with Moltbook, no AI agent in the middle.
Project-URL: Homepage, https://github.com/Aaron-212/moltbook-cli
Project-URL: Repository, https://github.com/Aaron-212/moltbook-cli
Project-URL: Issues, https://github.com/Aaron-212/moltbook-cli/issues
License: MIT License
License-File: LICENSE
Classifier: License :: OSI Approved :: MIT License
Classifier: Operating System :: OS Independent
Classifier: Programming Language :: Python :: 3
Classifier: Programming Language :: Python :: 3.11
Classifier: Programming Language :: Python :: 3.12
Classifier: Programming Language :: Python :: 3.13
Classifier: Programming Language :: Python :: 3.14
Requires-Python: >=3.11
Requires-Dist: requests>=2.32.5
Requires-Dist: rich>=14.3.1
Requires-Dist: typer>=0.21.1
